AUTHORS
CHANGES
INSTALL
LICENSE
MANIFEST.in
README.rst
nlopt.py
setup.py
bin/coconut.py
bin/coconut.sh
bin/sines.py
bin/sines.sh
bin/sines_rbf.py
bin/sines_rbf.sh
bin/test_obb
docs/html/.buildinfo
docs/html/genindex.html
docs/html/index.html
docs/html/install.html
docs/html/objects.inv
docs/html/search.html
docs/html/searchindex.js
docs/html/userguide.html
docs/html/_sources/index.txt
docs/html/_sources/install.txt
docs/html/_sources/userguide.txt
docs/html/_static/agogo.css
docs/html/_static/ajax-loader.gif
docs/html/_static/basic.css
docs/html/_static/bgfooter.png
docs/html/_static/bgtop.png
docs/html/_static/comment-bright.png
docs/html/_static/comment-close.png
docs/html/_static/comment.png
docs/html/_static/doctools.js
docs/html/_static/down-pressed.png
docs/html/_static/down.png
docs/html/_static/favicon.ico
docs/html/_static/file.png
docs/html/_static/jquery-1.11.1.js
docs/html/_static/jquery.js
docs/html/_static/minus.png
docs/html/_static/plus.png
docs/html/_static/pygments.css
docs/html/_static/searchtools.js
docs/html/_static/underscore-1.3.1.js
docs/html/_static/underscore.js
docs/html/_static/up-pressed.png
docs/html/_static/up.png
docs/html/_static/websupport.js
docs/html/_static/css/badge_only.css
docs/html/_static/css/theme.css
docs/html/_static/fonts/Inconsolata-Bold.ttf
docs/html/_static/fonts/Inconsolata-Regular.ttf
docs/html/_static/fonts/Lato-Bold.ttf
docs/html/_static/fonts/Lato-Regular.ttf
docs/html/_static/fonts/RobotoSlab-Bold.ttf
docs/html/_static/fonts/RobotoSlab-Regular.ttf
docs/html/_static/fonts/fontawesome-webfont.eot
docs/html/_static/fonts/fontawesome-webfont.svg
docs/html/_static/fonts/fontawesome-webfont.ttf
docs/html/_static/fonts/fontawesome-webfont.woff
docs/html/_static/js/modernizr.min.js
docs/html/_static/js/theme.js
docs/latex/oBB.pdf
nlopt/COPYRIGHT
nlopt/general.c
nlopt/nlopt-exceptions.i
nlopt/nlopt-internal.h
nlopt/nlopt-python.i
nlopt/nlopt-util.h
nlopt/nlopt.h
nlopt/nlopt.hpp
nlopt/nlopt.i
nlopt/nlopt_wrap.cxx
oBB.egg-info/PKG-INFO
oBB.egg-info/SOURCES.txt
oBB.egg-info/dependency_links.txt
oBB.egg-info/not-zip-safe
oBB.egg-info/requires.txt
oBB.egg-info/top_level.txt
