Metadata-Version: 1.0
Name: oBB
Version: 0.8b
Summary: Parallel global optimization of Hessian Lipschitz continuous functions.
Home-page: http://pypi.python.org/pypi/oBB/
Author: J. Fowkes
Author-email: jaroslav.fowkes@ed.ac.uk
License: LGPLv3
Platform: UNKNOWN
Classifier: Development Status :: 4 - Beta
Classifier: Intended Audience :: Science/Research
Classifier: License :: OSI Approved :: GNU Lesser General Public License v3 (LGPLv3)
Classifier: Natural Language :: English
Classifier: Operating System :: POSIX :: Linux
Classifier: Programming Language :: Python :: 2.6
Classifier: Programming Language :: Python :: 2.7
Classifier: Programming Language :: Python :: 3
Classifier: Topic :: Scientific/Engineering :: Mathematics
